{
  "id": "mama-bear",
  "name": "Mama Bear",
  "category": "Furniture",
  "games": {
    "nl": {
      "orderable": true,
      "interiorThemes": [
        "Fairy Tale",
        "Toy Shop"
      ],
      "set": "Bear",
      "sellPrice": {
        "currency": "bells",
        "value": 400
      },
      "sources": [
        "Nookling stores"
      ],
      "buyPrices": [
        {
          "currency": "bells",
          "value": 1600
        }
      ]
    },
    "nh": {
      "orderable": true,
      "sources": [
        "Nook's Cranny"
      ],
      "customizable": true,
      "sellPrice": {
        "currency": "bells",
        "value": 575
      },
      "buyPrices": [
        {
          "currency": "bells",
          "value": 2300
        }
      ],
      "variations": {
        "cream": "Cream",
        "cream-red-stripes": "Cream / Red stripes",
        "cream-blue-stripes": "Cream / Blue stripes",
        "cream-yellow-stripes": "Cream / Yellow stripes",
        "caramel-mocha": "Caramel mocha",
        "caramel-mocha-red-stripes": "Caramel mocha / Red stripes",
        "caramel-mocha-blue-stripes": "Caramel mocha / Blue stripes",
        "caramel-mocha-yellow-stripes": "Caramel mocha / Yellow stripes",
        "choco": "Choco",
        "choco-red-stripes": "Choco / Red stripes",
        "choco-blue-stripes": "Choco / Blue stripes",
        "choco-yellow-stripes": "Choco / Yellow stripes",
        "floral": "Floral",
        "floral-red-stripes": "Floral / Red stripes",
        "floral-blue-stripes": "Floral / Blue stripes",
        "floral-yellow-stripes": "Floral / Yellow stripes",
        "checkered": "Checkered",
        "checkered-red-stripes": "Checkered / Red stripes",
        "checkered-blue-stripes": "Checkered / Blue stripes",
        "checkered-yellow-stripes": "Checkered / Yellow stripes",
        "tweed": "Tweed",
        "tweed-red-stripes": "Tweed / Red stripes",
        "tweed-blue-stripes": "Tweed / Blue stripes",
        "tweed-yellow-stripes": "Tweed / Yellow stripes"
      }
    }
  }
}